{
  "type": "Program",
  "body": [
    {
      "type": "ImportDeclaration",
      "specifiers": [
        {
          "type": "ImportSpecifier",
          "local": {
            "type": "Identifier",
            "name": "_alloc",
            "range": [
              9,
              15
            ],
            "loc": {
              "start": {
                "line": 1,
                "column": 9
              },
              "end": {
                "line": 1,
                "column": 15
              }
            }
          },
          "imported": {
            "type": "Identifier",
            "name": "_alloc",
            "range": [
              9,
              15
            ],
            "loc": {
              "start": {
                "line": 1,
                "column": 9
              },
              "end": {
                "line": 1,
                "column": 15
              }
            }
          },
          "range": [
            9,
            15
          ],
          "loc": {
            "start": {
              "line": 1,
              "column": 9
            },
            "end": {
              "line": 1,
              "column": 15
            }
          }
        },
        {
          "type": "ImportSpecifier",
          "local": {
            "type": "Identifier",
            "name": "_reset",
            "range": [
              18,
              24
            ],
            "loc": {
              "start": {
                "line": 1,
                "column": 18
              },
              "end": {
                "line": 1,
                "column": 24
              }
            }
          },
          "imported": {
            "type": "Identifier",
            "name": "_reset",
            "range": [
              18,
              24
            ],
            "loc": {
              "start": {
                "line": 1,
                "column": 18
              },
              "end": {
                "line": 1,
                "column": 24
              }
            }
          },
          "range": [
            18,
            24
          ],
          "loc": {
            "start": {
              "line": 1,
              "column": 18
            },
            "end": {
              "line": 1,
              "column": 24
            }
          }
        }
      ],
      "source": {
        "type": "Literal",
        "value": "./",
        "raw": "'./'",
        "range": [
          32,
          36
        ],
        "loc": {
          "start": {
            "line": 1,
            "column": 32
          },
          "end": {
            "line": 1,
            "column": 36
          }
        }
      },
      "range": [
        0,
        38
      ],
      "loc": {
        "start": {
          "line": 1,
          "column": 0
        },
        "end": {
          "line": 1,
          "column": 38
        }
      }
    },
    {
      "type": "ExportNamedDeclaration",
      "declaration": {
        "type": "FunctionDeclaration",
        "id": {
          "type": "Identifier",
          "name": "_zeros",
          "range": [
            56,
            62
          ],
          "loc": {
            "start": {
              "line": 3,
              "column": 16
            },
            "end": {
              "line": 3,
              "column": 22
            }
          }
        },
        "params": [
          {
            "type": "Identifier",
            "name": "n",
            "range": [
              65,
              66
            ],
            "loc": {
              "start": {
                "line": 3,
                "column": 25
              },
              "end": {
                "line": 3,
                "column": 26
              }
            }
          }
        ],
        "body": {
          "type": "BlockStatement",
          "body": [
            {
              "type": "VariableDeclaration",
              "declarations": [
                {
                  "type": "VariableDeclarator",
                  "id": {
                    "type": "Identifier",
                    "name": "a",
                    "range": [
                      79,
                      80
                    ],
                    "loc": {
                      "start": {
                        "line": 5,
                        "column": 7
                      },
                      "end": {
                        "line": 5,
                        "column": 8
                      }
                    }
                  },
                  "init": {
                    "type": "CallExpression",
                    "callee": {
                      "type": "Identifier",
                      "name": "_alloc",
                      "range": [
                        83,
                        89
                      ],
                      "loc": {
                        "start": {
                          "line": 5,
                          "column": 11
                        },
                        "end": {
                          "line": 5,
                          "column": 17
                        }
                      }
                    },
                    "arguments": [
                      {
                        "type": "Identifier",
                        "name": "n",
                        "range": [
                          91,
                          92
                        ],
                        "loc": {
                          "start": {
                            "line": 5,
                            "column": 19
                          },
                          "end": {
                            "line": 5,
                            "column": 20
                          }
                        }
                      }
                    ],
                    "range": [
                      83,
                      94
                    ],
                    "loc": {
                      "start": {
                        "line": 5,
                        "column": 11
                      },
                      "end": {
                        "line": 5,
                        "column": 22
                      }
                    }
                  },
                  "range": [
                    79,
                    94
                  ],
                  "loc": {
                    "start": {
                      "line": 5,
                      "column": 7
                    },
                    "end": {
                      "line": 5,
                      "column": 22
                    }
                  }
                }
              ],
              "kind": "const",
              "range": [
                73,
                96
              ],
              "loc": {
                "start": {
                  "line": 5,
                  "column": 1
                },
                "end": {
                  "line": 5,
                  "column": 24
                }
              }
            },
            {
              "type": "ExpressionStatement",
              "expression": {
                "type": "CallExpression",
                "callee": {
                  "type": "Identifier",
                  "name": "_reset",
                  "range": [
                    99,
                    105
                  ],
                  "loc": {
                    "start": {
                      "line": 7,
                      "column": 1
                    },
                    "end": {
                      "line": 7,
                      "column": 7
                    }
                  }
                },
                "arguments": [
                  {
                    "type": "Identifier",
                    "name": "a",
                    "range": [
                      107,
                      108
                    ],
                    "loc": {
                      "start": {
                        "line": 7,
                        "column": 9
                      },
                      "end": {
                        "line": 7,
                        "column": 10
                      }
                    }
                  },
                  {
                    "type": "Literal",
                    "value": 0,
                    "raw": "0",
                    "range": [
                      111,
                      112
                    ],
                    "loc": {
                      "start": {
                        "line": 7,
                        "column": 13
                      },
                      "end": {
                        "line": 7,
                        "column": 14
                      }
                    }
                  },
                  {
                    "type": "Identifier",
                    "name": "n",
                    "range": [
                      115,
                      116
                    ],
                    "loc": {
                      "start": {
                        "line": 7,
                        "column": 17
                      },
                      "end": {
                        "line": 7,
                        "column": 18
                      }
                    }
                  }
                ],
                "range": [
                  99,
                  118
                ],
                "loc": {
                  "start": {
                    "line": 7,
                    "column": 1
                  },
                  "end": {
                    "line": 7,
                    "column": 20
                  }
                }
              },
              "range": [
                99,
                120
              ],
              "loc": {
                "start": {
                  "line": 7,
                  "column": 1
                },
                "end": {
                  "line": 7,
                  "column": 22
                }
              }
            },
            {
              "type": "ReturnStatement",
              "argument": {
                "type": "Identifier",
                "name": "a",
                "range": [
                  130,
                  131
                ],
                "loc": {
                  "start": {
                    "line": 9,
                    "column": 8
                  },
                  "end": {
                    "line": 9,
                    "column": 9
                  }
                }
              },
              "range": [
                123,
                133
              ],
              "loc": {
                "start": {
                  "line": 9,
                  "column": 1
                },
                "end": {
                  "line": 9,
                  "column": 11
                }
              }
            }
          ],
          "range": [
            69,
            136
          ],
          "loc": {
            "start": {
              "line": 3,
              "column": 29
            },
            "end": {
              "line": 11,
              "column": 1
            }
          }
        },
        "generator": false,
        "expression": false,
        "range": [
          47,
          136
        ],
        "loc": {
          "start": {
            "line": 3,
            "column": 7
          },
          "end": {
            "line": 11,
            "column": 1
          }
        },
        "leadingComments": [],
        "trailingComments": []
      },
      "specifiers": [],
      "source": null,
      "range": [
        40,
        136
      ],
      "loc": {
        "start": {
          "line": 3,
          "column": 0
        },
        "end": {
          "line": 11,
          "column": 1
        }
      }
    }
  ],
  "sourceType": "module",
  "range": [
    0,
    136
  ],
  "loc": {
    "start": {
      "line": 1,
      "column": 0
    },
    "end": {
      "line": 11,
      "column": 1
    }
  },
  "comments": []
}